prefect_multiprocess/__init__.py
prefect_multiprocess/_version.py
prefect_multiprocess/task_runners.py
prefect_multiprocess/utilities/__init__.py
prefect_multiprocess/utilities/collections.py
prefect_multiprocess/utilities/remote.py
prefect_multiprocess-0.1.2.dist-info/LICENSE
prefect_multiprocess-0.1.2.dist-info/METADATA
prefect_multiprocess-0.1.2.dist-info/WHEEL
prefect_multiprocess-0.1.2.dist-info/top_level.txt
prefect_multiprocess-0.1.2.dist-info/RECORD
