Metadata-Version: 2.1
Name: prefect-multiprocess
Version: 0.1.2
Summary: A multiprocess task runner for Prefect 2.8.3+.
Home-page: https://github.com/rpeden/prefect-multiprocess
Author: Ryan Peden
Author-email: ryan@rpeden.com
License: Apache License 2.0
Keywords: prefect
Classifier: Natural Language :: English
Classifier: Intended Audience :: Developers
Classifier: Intended Audience :: System Administrators
Classifier: License :: OSI Approved :: Apache Software License
Classifier: Programming Language :: Python :: 3 :: Only
Classifier: Programming Language :: Python :: 3.8
Classifier: Programming Language :: Python :: 3.9
Classifier: Programming Language :: Python :: 3.10
Classifier: Topic :: Software Development :: Libraries
Requires-Python: >=3.8
License-File: LICENSE
Requires-Dist: prefect >=2.8.3
Provides-Extra: dev
Requires-Dist: pytest ; extra == 'dev'
Requires-Dist: black ; extra == 'dev'
Requires-Dist: flake8 ; extra == 'dev'
Requires-Dist: mypy ; extra == 'dev'
Requires-Dist: mkdocs ; extra == 'dev'
Requires-Dist: mkdocs-material ; extra == 'dev'
Requires-Dist: mkdocstrings-python ; extra == 'dev'
Requires-Dist: isort ; extra == 'dev'
Requires-Dist: pre-commit ; extra == 'dev'
Requires-Dist: pytest-asyncio ; extra == 'dev'
Requires-Dist: mkdocs-gen-files ; extra == 'dev'
Requires-Dist: interrogate ; extra == 'dev'
Requires-Dist: coverage ; extra == 'dev'
Requires-Dist: pillow ; extra == 'dev'
Requires-Dist: mock ; (python_version < "3.8") and extra == 'dev'
